sottek_hearing_model/__init__.py
sottek_hearing_model/filters.py
sottek_hearing_model/plotting_tools.py
sottek_hearing_model/py.typed
sottek_hearing_model/shm_loudness_ecma.py
sottek_hearing_model/shm_reference_signals.py
sottek_hearing_model/shm_roughness_ecma.py
sottek_hearing_model/shm_subs.py
sottek_hearing_model/shm_tonality_ecma.py
sottek_hearing_model-0.1.12.dist-info/WHEEL
sottek_hearing_model-0.1.12.dist-info/METADATA
sottek_hearing_model-0.1.12.dist-info/RECORD
