Metadata-Version: 2.4
Name: sottek-hearing-model
Version: 0.1.12
Summary: Implements algorithms from the Sottek Hearing Model
Author: Mike Lotinga
Author-email: Mike Lotinga <m.j.lotinga@edu.salford.ac.uk>
License-Expression: AGPL-3.0-only
Requires-Dist: bottleneck>=1.6.0
Requires-Dist: matplotlib>=3.9
Requires-Dist: numpy>=2.2.6
Requires-Dist: pyqt6>=6.9.1
Requires-Dist: scipy>=1.16.2
Requires-Dist: tqdm>=4.67.1
Requires-Python: >=3.11
Project-URL: Documentation, https://github.com/mlotinga/sottek-hearing-model/
Project-URL: Homepage, https://github.com/mlotinga/sottek-hearing-model
Project-URL: Issues, https://github.com/mlotinga/sottek-hearing-model/issues
Project-URL: Repository, https://github.com/mlotinga/sottek-hearing-model
